[
  { "id": "fireflower", "name": "Огнецвет", "element": "fire", "grow_time_minutes": 15, "cost": 10, "native_biome": "volcanic", "sprite": "plants/fireflower", "description": "Алый цветок, лепестки которого тлеют как угли. Самая частая культура архипелага." },
  { "id": "lava_berry", "name": "Лавовая Ягода", "element": "fire", "grow_time_minutes": 30, "cost": 20, "native_biome": "volcanic", "sprite": "plants/lava_berry", "description": "Жгучая ягода с застывших потоков лавы. Любимое лакомство Эмберикса (+20%)." },
  { "id": "hot_moss", "name": "Жаркий Мох", "element": "fire", "grow_time_minutes": 45, "cost": 30, "native_biome": "volcanic", "sprite": "plants/hot_moss", "description": "Тлеет, но не сгорает. Повышает шанс гибрида в скрещивании Огонь+Земля." },
  { "id": "sea_flower", "name": "Морской Цветок", "element": "water", "grow_time_minutes": 20, "cost": 14, "native_biome": "lunar", "sprite": "plants/sea_flower", "description": "Нежный синий цветок, раскрывающийся только в лунном свете. Основа водных рецептов." },
  { "id": "pearl_moss", "name": "Жемчужный Мох", "element": "water", "grow_time_minutes": 40, "cost": 26, "native_biome": "lunar", "sprite": "plants/pearl_moss", "description": "Мягкий мох с перламутровыми бусинами росы. Любимая еда Акваринта (+20%)." },
  { "id": "root_of_power", "name": "Корень Силы", "element": "earth", "grow_time_minutes": 25, "cost": 17, "native_biome": "crystal", "sprite": "plants/root_of_power", "description": "Толстый узловатый корень, налитый силой земли. Основа земляных рецептов." },
  { "id": "stone_fruit", "name": "Каменный Плод", "element": "earth", "grow_time_minutes": 60, "cost": 40, "native_biome": "crystal", "sprite": "plants/stone_fruit", "description": "Твёрдый снаружи, сочный внутри. Любимая еда Терравора (+20%)." },
  { "id": "storm_pepper", "name": "Грозовой Перец", "element": "storm", "grow_time_minutes": 20, "cost": 14, "native_biome": "storm", "sprite": "plants/storm_pepper", "description": "Острый перец, искрящийся статикой при касании. Основа грозовых рецептов." },
  { "id": "ice_rose", "name": "Ледяная Роза", "element": "ice", "grow_time_minutes": 30, "cost": 20, "native_biome": "ice", "sprite": "plants/ice_rose", "description": "Роза, выкованная будто изо льда. Основа ледяных рецептов. Не тает в тепле." },
  { "id": "snow_mushroom", "name": "Снежный Гриб", "element": "ice", "grow_time_minutes": 90, "cost": 55, "native_biome": "ice", "sprite": "plants/snow_mushroom", "description": "Холодный гриб вечной мерзлоты. Любимая еда Фростела (+20%)." },
  { "id": "moon_lotus", "name": "Лунный Лотос", "element": "neutral", "grow_time_minutes": 120, "cost": 70, "native_biome": "any", "sprite": "plants/moon_lotus", "description": "Серебристый лотос, цветущий ночью. Нейтрален, нужен для большинства водных гибридов." },
  { "id": "electric_truffle", "name": "Электрический Трюфель", "element": "storm", "grow_time_minutes": 120, "cost": 70, "native_biome": "storm", "sprite": "plants/electric_truffle", "description": "Светящийся трюфель из наэлектризованной почвы. Любимая еда Вольтракса (+20%). Капризен — растёт долго." },
  { "id": "air_dandelion", "name": "Воздушный Одуванчик", "element": "wind", "grow_time_minutes": 15, "cost": 10, "native_biome": "air", "sprite": "plants/air_dandelion", "description": "Пушистый одуванчик, чьи семена вечно парят в воздухе. Любимая еда Зефира (+20%) и основа воздушных рецептов." },
  { "id": "feather_grass", "name": "Перо-трава", "element": "wind", "grow_time_minutes": 40, "cost": 26, "native_biome": "air", "sprite": "plants/feather_grass", "description": "Высокая трава с листьями-перьями, колышущаяся даже в полный штиль. Нужна для ветряных гибридов." },
  { "id": "life_flower", "name": "Цветок Жизни", "element": "nature", "grow_time_minutes": 20, "cost": 14, "native_biome": "nature", "sprite": "plants/life_flower", "description": "Яркий цветок, светящийся жизненной силой. Любимая еда Сильвена (+20%) и основа природных рецептов." },
  { "id": "sweet_root", "name": "Сладкий Корень", "element": "nature", "grow_time_minutes": 45, "cost": 30, "native_biome": "nature", "sprite": "plants/sweet_root", "description": "Сладкий хрустящий корень. Нужен для выведения природных гибридов (Эмберлиф, Блумтайд)." }
]
